[
    {
        "id": 2740118865,
        "run_id": 903911933,
        "run_url": "https://api.github.com/repos/elisemorysc/hunter/actions/runs/903911933",
        "node_id": "MDg6Q2hlY2tSdW4yNzQwMTE4ODY1",
        "head_sha": "298c69fd3cb5561e1349604ceb0a1b3f57ef408e",
        "url": "https://api.github.com/repos/elisemorysc/hunter/actions/jobs/2740118865",
        "html_url": "https://github.com/elisemorysc/hunter/runs/2740118865",
        "status": "completed",
        "conclusion": "failure",
        "started_at": "2021-06-03T19:12:29Z",
        "completed_at": "2021-06-03T19:13:04Z",
        "name": "CURL analyze-cxx17 ubuntu-16.04",
        "steps": [
            {
                "name": "Set up job",
                "status": "completed",
                "conclusion": "success",
                "number": 1,
                "started_at": "2021-06-03T19:12:29.000Z",
                "completed_at": "2021-06-03T19:12:31.000Z"
            },
            {
                "name": "Git checkout with submodules",
                "status": "completed",
                "conclusion": "success",
                "number": 2,
                "started_at": "2021-06-03T19:12:31.000Z",
                "completed_at": "2021-06-03T19:12:35.000Z"
            },
            {
                "name": "Set up Python",
                "status": "completed",
                "conclusion": "success",
                "number": 3,
                "started_at": "2021-06-03T19:12:35.000Z",
                "completed_at": "2021-06-03T19:12:35.000Z"
            },
            {
                "name": "Set up Python environment variable (Unix)",
                "status": "completed",
                "conclusion": "success",
                "number": 4,
                "started_at": "2021-06-03T19:12:35.000Z",
                "completed_at": "2021-06-03T19:12:35.000Z"
            },
            {
                "name": "Set up Python environment variable (Windows)",
                "status": "completed",
                "conclusion": "skipped",
                "number": 5,
                "started_at": "2021-06-03T19:12:35.000Z",
                "completed_at": "2021-06-03T19:12:35.000Z"
            },
            {
                "name": "Extract branch name",
                "status": "completed",
                "conclusion": "success",
                "number": 6,
                "started_at": "2021-06-03T19:12:35.000Z",
                "completed_at": "2021-06-03T19:12:35.000Z"
            },
            {
                "name": "Build on Unix",
                "status": "completed",
                "conclusion": "failure",
                "number": 7,
                "started_at": "2021-06-03T19:12:35.000Z",
                "completed_at": "2021-06-03T19:13:03.000Z"
            },
            {
                "name": "Build on Windows",
                "status": "completed",
                "conclusion": "skipped",
                "number": 8,
                "started_at": "2021-06-03T19:13:03.000Z",
                "completed_at": "2021-06-03T19:13:03.000Z"
            },
            {
                "name": "Post Git checkout with submodules",
                "status": "completed",
                "conclusion": "success",
                "number": 16,
                "started_at": "2021-06-03T19:13:03.000Z",
                "completed_at": "2021-06-03T19:13:04.000Z"
            },
            {
                "name": "Complete job",
                "status": "completed",
                "conclusion": "success",
                "number": 17,
                "started_at": "2021-06-03T19:13:04.000Z",
                "completed_at": "2021-06-03T19:13:04.000Z"
            }
        ],
        "check_run_url": "https://api.github.com/repos/elisemorysc/hunter/check-runs/2740118865"
    },
    {
        "id": 2740118853,
        "run_id": 903911933,
        "run_url": "https://api.github.com/repos/elisemorysc/hunter/actions/runs/903911933",
        "node_id": "MDg6Q2hlY2tSdW4yNzQwMTE4ODUz",
        "head_sha": "298c69fd3cb5561e1349604ceb0a1b3f57ef408e",
        "url": "https://api.github.com/repos/elisemorysc/hunter/actions/jobs/2740118853",
        "html_url": "https://github.com/elisemorysc/hunter/runs/2740118853",
        "status": "completed",
        "conclusion": "success",
        "started_at": "2021-06-03T19:12:13Z",
        "completed_at": "2021-06-03T19:13:30Z",
        "name": "CURL android-ndk-r17-api-24-arm64-v8a-clang-libcxx14 ubuntu-16.04",
        "steps": [
            {
                "name": "Set up job",
                "status": "completed",
                "conclusion": "success",
                "number": 1,
                "started_at": "2021-06-03T19:12:13.000Z",
                "completed_at": "2021-06-03T19:12:16.000Z"
            },
            {
                "name": "Git checkout with submodules",
                "status": "completed",
                "conclusion": "success",
                "number": 2,
                "started_at": "2021-06-03T19:12:16.000Z",
                "completed_at": "2021-06-03T19:12:22.000Z"
            },
            {
                "name": "Set up Python",
                "status": "completed",
                "conclusion": "success",
                "number": 3,
                "started_at": "2021-06-03T19:12:22.000Z",
                "completed_at": "2021-06-03T19:12:22.000Z"
            },
            {
                "name": "Set up Python environment variable (Unix)",
                "status": "completed",
                "conclusion": "success",
                "number": 4,
                "started_at": "2021-06-03T19:12:22.000Z",
                "completed_at": "2021-06-03T19:12:22.000Z"
            },
            {
                "name": "Set up Python environment variable (Windows)",
                "status": "completed",
                "conclusion": "skipped",
                "number": 5,
                "started_at": "2021-06-03T19:12:22.000Z",
                "completed_at": "2021-06-03T19:12:22.000Z"
            },
            {
                "name": "Extract branch name",
                "status": "completed",
                "conclusion": "success",
                "number": 6,
                "started_at": "2021-06-03T19:12:22.000Z",
                "completed_at": "2021-06-03T19:12:22.000Z"
            },
            {
                "name": "Build on Unix",
                "status": "completed",
                "conclusion": "success",
                "number": 7,
                "started_at": "2021-06-03T19:12:22.000Z",
                "completed_at": "2021-06-03T19:13:30.000Z"
            },
            {
                "name": "Build on Windows",
                "status": "completed",
                "conclusion": "skipped",
                "number": 8,
                "started_at": "2021-06-03T19:13:30.000Z",
                "completed_at": "2021-06-03T19:13:30.000Z"
            },
            {
                "name": "Post Git checkout with submodules",
                "status": "completed",
                "conclusion": "success",
                "number": 16,
                "started_at": "2021-06-03T19:13:30.000Z",
                "completed_at": "2021-06-03T19:13:30.000Z"
            },
            {
                "name": "Complete job",
                "status": "completed",
                "conclusion": "success",
                "number": 17,
                "started_at": "2021-06-03T19:13:30.000Z",
                "completed_at": "2021-06-03T19:13:30.000Z"
            }
        ],
        "check_run_url": "https://api.github.com/repos/elisemorysc/hunter/check-runs/2740118853"
    },
    {
        "id": 2740118763,
        "run_id": 903911933,
        "run_url": "https://api.github.com/repos/elisemorysc/hunter/actions/runs/903911933",
        "node_id": "MDg6Q2hlY2tSdW4yNzQwMTE4NzYz",
        "head_sha": "298c69fd3cb5561e1349604ceb0a1b3f57ef408e",
        "url": "https://api.github.com/repos/elisemorysc/hunter/actions/jobs/2740118763",
        "html_url": "https://github.com/elisemorysc/hunter/runs/2740118763",
        "status": "completed",
        "conclusion": "success",
        "started_at": "2021-06-03T19:12:34Z",
        "completed_at": "2021-06-03T19:13:07Z",
        "name": "CURL clang-cxx17 ubuntu-16.04",
        "steps": [
            {
                "name": "Set up job",
                "status": "completed",
                "conclusion": "success",
                "number": 1,
                "started_at": "2021-06-03T19:12:34.000Z",
                "completed_at": "2021-06-03T19:12:37.000Z"
            },
            {
                "name": "Git checkout with submodules",
                "status": "completed",
                "conclusion": "success",
                "number": 2,
                "started_at": "2021-06-03T19:12:37.000Z",
                "completed_at": "2021-06-03T19:12:42.000Z"
            },
            {
                "name": "Set up Python",
                "status": "completed",
                "conclusion": "success",
                "number": 3,
                "started_at": "2021-06-03T19:12:42.000Z",
                "completed_at": "2021-06-03T19:12:42.000Z"
            },
            {
                "name": "Set up Python environment variable (Unix)",
                "status": "completed",
                "conclusion": "success",
                "number": 4,
                "started_at": "2021-06-03T19:12:42.000Z",
                "completed_at": "2021-06-03T19:12:42.000Z"
            },
            {
                "name": "Set up Python environment variable (Windows)",
                "status": "completed",
                "conclusion": "skipped",
                "number": 5,
                "started_at": "2021-06-03T19:12:42.000Z",
                "completed_at": "2021-06-03T19:12:42.000Z"
            },
            {
                "name": "Extract branch name",
                "status": "completed",
                "conclusion": "success",
                "number": 6,
                "started_at": "2021-06-03T19:12:42.000Z",
                "completed_at": "2021-06-03T19:12:42.000Z"
            },
            {
                "name": "Build on Unix",
                "status": "completed",
                "conclusion": "success",
                "number": 7,
                "started_at": "2021-06-03T19:12:42.000Z",
                "completed_at": "2021-06-03T19:13:06.000Z"
            },
            {
                "name": "Build on Windows",
                "status": "completed",
                "conclusion": "skipped",
                "number": 8,
                "started_at": "2021-06-03T19:13:06.000Z",
                "completed_at": "2021-06-03T19:13:06.000Z"
            },
            {
                "name": "Post Git checkout with submodules",
                "status": "completed",
                "conclusion": "success",
                "number": 16,
                "started_at": "2021-06-03T19:13:06.000Z",
                "completed_at": "2021-06-03T19:13:07.000Z"
            },
            {
                "name": "Complete job",
                "status": "completed",
                "conclusion": "success",
                "number": 17,
                "started_at": "2021-06-03T19:13:07.000Z",
                "completed_at": "2021-06-03T19:13:07.000Z"
            }
        ],
        "check_run_url": "https://api.github.com/repos/elisemorysc/hunter/check-runs/2740118763"
    },
    {
        "id": 2740118788,
        "run_id": 903911933,
        "run_url": "https://api.github.com/repos/elisemorysc/hunter/actions/runs/903911933",
        "node_id": "MDg6Q2hlY2tSdW4yNzQwMTE4Nzg4",
        "head_sha": "298c69fd3cb5561e1349604ceb0a1b3f57ef408e",
        "url": "https://api.github.com/repos/elisemorysc/hunter/actions/jobs/2740118788",
        "html_url": "https://github.com/elisemorysc/hunter/runs/2740118788",
        "status": "completed",
        "conclusion": "success",
        "started_at": "2021-06-03T19:12:38Z",
        "completed_at": "2021-06-03T19:13:25Z",
        "name": "CURL gcc-7-cxx17 ubuntu-16.04",
        "steps": [
            {
                "name": "Set up job",
                "status": "completed",
                "conclusion": "success",
                "number": 1,
                "started_at": "2021-06-03T19:12:38.000Z",
                "completed_at": "2021-06-03T19:12:42.000Z"
            },
            {
                "name": "Git checkout with submodules",
                "status": "completed",
                "conclusion": "success",
                "number": 2,
                "started_at": "2021-06-03T19:12:42.000Z",
                "completed_at": "2021-06-03T19:12:47.000Z"
            },
            {
                "name": "Set up Python",
                "status": "completed",
                "conclusion": "success",
                "number": 3,
                "started_at": "2021-06-03T19:12:47.000Z",
                "completed_at": "2021-06-03T19:12:47.000Z"
            },
            {
                "name": "Set up Python environment variable (Unix)",
                "status": "completed",
                "conclusion": "success",
                "number": 4,
                "started_at": "2021-06-03T19:12:47.000Z",
                "completed_at": "2021-06-03T19:12:47.000Z"
            },
            {
                "name": "Set up Python environment variable (Windows)",
                "status": "completed",
                "conclusion": "skipped",
                "number": 5,
                "started_at": "2021-06-03T19:12:47.000Z",
                "completed_at": "2021-06-03T19:12:47.000Z"
            },
            {
                "name": "Extract branch name",
                "status": "completed",
                "conclusion": "success",
                "number": 6,
                "started_at": "2021-06-03T19:12:47.000Z",
                "completed_at": "2021-06-03T19:12:47.000Z"
            },
            {
                "name": "Build on Unix",
                "status": "completed",
                "conclusion": "success",
                "number": 7,
                "started_at": "2021-06-03T19:12:47.000Z",
                "completed_at": "2021-06-03T19:13:24.000Z"
            },
            {
                "name": "Build on Windows",
                "status": "completed",
                "conclusion": "skipped",
                "number": 8,
                "started_at": "2021-06-03T19:13:24.000Z",
                "completed_at": "2021-06-03T19:13:24.000Z"
            },
            {
                "name": "Post Git checkout with submodules",
                "status": "completed",
                "conclusion": "success",
                "number": 16,
                "started_at": "2021-06-03T19:13:24.000Z",
                "completed_at": "2021-06-03T19:13:25.000Z"
            },
            {
                "name": "Complete job",
                "status": "completed",
                "conclusion": "success",
                "number": 17,
                "started_at": "2021-06-03T19:13:25.000Z",
                "completed_at": "2021-06-03T19:13:25.000Z"
            }
        ],
        "check_run_url": "https://api.github.com/repos/elisemorysc/hunter/check-runs/2740118788"
    },
    {
        "id": 2740118809,
        "run_id": 903911933,
        "run_url": "https://api.github.com/repos/elisemorysc/hunter/actions/runs/903911933",
        "node_id": "MDg6Q2hlY2tSdW4yNzQwMTE4ODA5",
        "head_sha": "298c69fd3cb5561e1349604ceb0a1b3f57ef408e",
        "url": "https://api.github.com/repos/elisemorysc/hunter/actions/jobs/2740118809",
        "html_url": "https://github.com/elisemorysc/hunter/runs/2740118809",
        "status": "completed",
        "conclusion": "success",
        "started_at": "2021-06-03T19:12:38Z",
        "completed_at": "2021-06-03T19:13:14Z",
        "name": "CURL gcc-8-cxx17-fpic ubuntu-18.04",
        "steps": [
            {
                "name": "Set up job",
                "status": "completed",
                "conclusion": "success",
                "number": 1,
                "started_at": "2021-06-03T19:12:38.000Z",
                "completed_at": "2021-06-03T19:12:40.000Z"
            },
            {
                "name": "Git checkout with submodules",
                "status": "completed",
                "conclusion": "success",
                "number": 2,
                "started_at": "2021-06-03T19:12:40.000Z",
                "completed_at": "2021-06-03T19:12:44.000Z"
            },
            {
                "name": "Set up Python",
                "status": "completed",
                "conclusion": "success",
                "number": 3,
                "started_at": "2021-06-03T19:12:44.000Z",
                "completed_at": "2021-06-03T19:12:44.000Z"
            },
            {
                "name": "Set up Python environment variable (Unix)",
                "status": "completed",
                "conclusion": "success",
                "number": 4,
                "started_at": "2021-06-03T19:12:44.000Z",
                "completed_at": "2021-06-03T19:12:44.000Z"
            },
            {
                "name": "Set up Python environment variable (Windows)",
                "status": "completed",
                "conclusion": "skipped",
                "number": 5,
                "started_at": "2021-06-03T19:12:44.000Z",
                "completed_at": "2021-06-03T19:12:44.000Z"
            },
            {
                "name": "Extract branch name",
                "status": "completed",
                "conclusion": "success",
                "number": 6,
                "started_at": "2021-06-03T19:12:44.000Z",
                "completed_at": "2021-06-03T19:12:44.000Z"
            },
            {
                "name": "Build on Unix",
                "status": "completed",
                "conclusion": "success",
                "number": 7,
                "started_at": "2021-06-03T19:12:44.000Z",
                "completed_at": "2021-06-03T19:13:14.000Z"
            },
            {
                "name": "Build on Windows",
                "status": "completed",
                "conclusion": "skipped",
                "number": 8,
                "started_at": "2021-06-03T19:13:14.000Z",
                "completed_at": "2021-06-03T19:13:14.000Z"
            },
            {
                "name": "Post Git checkout with submodules",
                "status": "completed",
                "conclusion": "success",
                "number": 16,
                "started_at": "2021-06-03T19:13:14.000Z",
                "completed_at": "2021-06-03T19:13:14.000Z"
            },
            {
                "name": "Complete job",
                "status": "completed",
                "conclusion": "success",
                "number": 17,
                "started_at": "2021-06-03T19:13:14.000Z",
                "completed_at": "2021-06-03T19:13:14.000Z"
            }
        ],
        "check_run_url": "https://api.github.com/repos/elisemorysc/hunter/check-runs/2740118809"
    },
    {
        "id": 2740118830,
        "run_id": 903911933,
        "run_url": "https://api.github.com/repos/elisemorysc/hunter/actions/runs/903911933",
        "node_id": "MDg6Q2hlY2tSdW4yNzQwMTE4ODMw",
        "head_sha": "298c69fd3cb5561e1349604ceb0a1b3f57ef408e",
        "url": "https://api.github.com/repos/elisemorysc/hunter/actions/jobs/2740118830",
        "html_url": "https://github.com/elisemorysc/hunter/runs/2740118830",
        "status": "completed",
        "conclusion": "success",
        "started_at": "2021-06-03T19:13:11Z",
        "completed_at": "2021-06-03T19:13:47Z",
        "name": "CURL gcc-9-cxx17-fpic ubuntu-20.04",
        "steps": [
            {
                "name": "Set up job",
                "status": "completed",
                "conclusion": "success",
                "number": 1,
                "started_at": "2021-06-03T19:13:11.000Z",
                "completed_at": "2021-06-03T19:13:14.000Z"
            },
            {
                "name": "Git checkout with submodules",
                "status": "completed",
                "conclusion": "success",
                "number": 2,
                "started_at": "2021-06-03T19:13:14.000Z",
                "completed_at": "2021-06-03T19:13:19.000Z"
            },
            {
                "name": "Set up Python",
                "status": "completed",
                "conclusion": "success",
                "number": 3,
                "started_at": "2021-06-03T19:13:19.000Z",
                "completed_at": "2021-06-03T19:13:20.000Z"
            },
            {
                "name": "Set up Python environment variable (Unix)",
                "status": "completed",
                "conclusion": "success",
                "number": 4,
                "started_at": "2021-06-03T19:13:20.000Z",
                "completed_at": "2021-06-03T19:13:20.000Z"
            },
            {
                "name": "Set up Python environment variable (Windows)",
                "status": "completed",
                "conclusion": "skipped",
                "number": 5,
                "started_at": "2021-06-03T19:13:20.000Z",
                "completed_at": "2021-06-03T19:13:20.000Z"
            },
            {
                "name": "Extract branch name",
                "status": "completed",
                "conclusion": "success",
                "number": 6,
                "started_at": "2021-06-03T19:13:20.000Z",
                "completed_at": "2021-06-03T19:13:20.000Z"
            },
            {
                "name": "Build on Unix",
                "status": "completed",
                "conclusion": "success",
                "number": 7,
                "started_at": "2021-06-03T19:13:20.000Z",
                "completed_at": "2021-06-03T19:13:46.000Z"
            },
            {
                "name": "Build on Windows",
                "status": "completed",
                "conclusion": "skipped",
                "number": 8,
                "started_at": "2021-06-03T19:13:46.000Z",
                "completed_at": "2021-06-03T19:13:46.000Z"
            },
            {
                "name": "Post Git checkout with submodules",
                "status": "completed",
                "conclusion": "success",
                "number": 16,
                "started_at": "2021-06-03T19:13:46.000Z",
                "completed_at": "2021-06-03T19:13:47.000Z"
            },
            {
                "name": "Complete job",
                "status": "completed",
                "conclusion": "success",
                "number": 17,
                "started_at": "2021-06-03T19:13:47.000Z",
                "completed_at": "2021-06-03T19:13:47.000Z"
            }
        ],
        "check_run_url": "https://api.github.com/repos/elisemorysc/hunter/check-runs/2740118830"
    },
    {
        "id": 2740118888,
        "run_id": 903911933,
        "run_url": "https://api.github.com/repos/elisemorysc/hunter/actions/runs/903911933",
        "node_id": "MDg6Q2hlY2tSdW4yNzQwMTE4ODg4",
        "head_sha": "298c69fd3cb5561e1349604ceb0a1b3f57ef408e",
        "url": "https://api.github.com/repos/elisemorysc/hunter/actions/jobs/2740118888",
        "html_url": "https://github.com/elisemorysc/hunter/runs/2740118888",
        "status": "completed",
        "conclusion": "success",
        "started_at": "2021-06-03T19:13:38Z",
        "completed_at": "2021-06-03T19:14:19Z",
        "name": "CURL sanitize-address-cxx17 ubuntu-16.04",
        "steps": [
            {
                "name": "Set up job",
                "status": "completed",
                "conclusion": "success",
                "number": 1,
                "started_at": "2021-06-03T19:13:38.000Z",
                "completed_at": "2021-06-03T19:13:41.000Z"
            },
            {
                "name": "Git checkout with submodules",
                "status": "completed",
                "conclusion": "success",
                "number": 2,
                "started_at": "2021-06-03T19:13:41.000Z",
                "completed_at": "2021-06-03T19:13:45.000Z"
            },
            {
                "name": "Set up Python",
                "status": "completed",
                "conclusion": "success",
                "number": 3,
                "started_at": "2021-06-03T19:13:45.000Z",
                "completed_at": "2021-06-03T19:13:45.000Z"
            },
            {
                "name": "Set up Python environment variable (Unix)",
                "status": "completed",
                "conclusion": "success",
                "number": 4,
                "started_at": "2021-06-03T19:13:45.000Z",
                "completed_at": "2021-06-03T19:13:45.000Z"
            },
            {
                "name": "Set up Python environment variable (Windows)",
                "status": "completed",
                "conclusion": "skipped",
                "number": 5,
                "started_at": "2021-06-03T19:13:45.000Z",
                "completed_at": "2021-06-03T19:13:45.000Z"
            },
            {
                "name": "Extract branch name",
                "status": "completed",
                "conclusion": "success",
                "number": 6,
                "started_at": "2021-06-03T19:13:45.000Z",
                "completed_at": "2021-06-03T19:13:45.000Z"
            },
            {
                "name": "Build on Unix",
                "status": "completed",
                "conclusion": "success",
                "number": 7,
                "started_at": "2021-06-03T19:13:45.000Z",
                "completed_at": "2021-06-03T19:14:19.000Z"
            },
            {
                "name": "Build on Windows",
                "status": "completed",
                "conclusion": "skipped",
                "number": 8,
                "started_at": "2021-06-03T19:14:19.000Z",
                "completed_at": "2021-06-03T19:14:19.000Z"
            },
            {
                "name": "Post Git checkout with submodules",
                "status": "completed",
                "conclusion": "success",
                "number": 16,
                "started_at": "2021-06-03T19:14:19.000Z",
                "completed_at": "2021-06-03T19:14:19.000Z"
            },
            {
                "name": "Complete job",
                "status": "completed",
                "conclusion": "success",
                "number": 17,
                "started_at": "2021-06-03T19:14:19.000Z",
                "completed_at": "2021-06-03T19:14:19.000Z"
            }
        ],
        "check_run_url": "https://api.github.com/repos/elisemorysc/hunter/check-runs/2740118888"
    }
]